lisa/globalfit/framework/__init__.py
lisa/globalfit/framework/args.py
lisa/globalfit/framework/bus.py
lisa/globalfit/framework/catalog.py
lisa/globalfit/framework/cli.py
lisa/globalfit/framework/exceptions.py
lisa/globalfit/framework/io.py
lisa/globalfit/framework/logging.py
lisa/globalfit/framework/mock_engine.py
lisa/globalfit/framework/model.py
lisa/globalfit/framework/plot.py
lisa/globalfit/framework/preprocessing.py
lisa/globalfit/framework/signal.py
lisa/globalfit/framework/simulator.py
lisa/globalfit/framework/waveform.py
lisa/globalfit/framework/buses/__init__.py
lisa/globalfit/framework/buses/nats.py
lisa/globalfit/framework/catalogs/memory.py
lisa/globalfit/framework/catalogs/sqlite.py
lisa/globalfit/framework/engine/__init__.py
lisa/globalfit/framework/engine/cli.py
lisa/globalfit/framework/engine/engine.py
lisa/globalfit/framework/engine/rule.py
lisa/globalfit/framework/modules/__init__.py
lisa/globalfit/framework/modules/module.py
lisa/globalfit/framework/modules/pool.py
lisa/globalfit/framework/modules/registry.py
lisa/globalfit/framework/modules/stub/__init__.py
lisa/globalfit/framework/modules/stub/module.py
lisa/globalfit/framework/modules/stub/preprocessor.py
lisa/globalfit/framework/monitoring/__init__.py
lisa/globalfit/framework/monitoring/api.py
lisa/globalfit/framework/monitoring/server.py
lisa/globalfit/framework/monitoring/service.py
lisa/globalfit/framework/monitoring/types.py
lisa/globalfit/framework/monitoring/ui.py
lisa/globalfit/framework/monitoring/static/__init__.py
lisa/globalfit/framework/monitoring/static/style.css
lisa/globalfit/framework/monitoring/templates/__init__.py
lisa/globalfit/framework/monitoring/templates/base.html
lisa/globalfit/framework/monitoring/templates/index.html
lisa/globalfit/framework/monitoring/templates/module_details.html
lisa/globalfit/framework/monitoring/templates/run_details.html
lisa/globalfit/framework/monitoring/templates/runs.html
lisa/globalfit/framework/msg/__init__.py
lisa_globalfit_framework-0.7.1.dist-info/METADATA
lisa_globalfit_framework-0.7.1.dist-info/WHEEL
lisa_globalfit_framework-0.7.1.dist-info/entry_points.txt
lisa_globalfit_framework-0.7.1.dist-info/top_level.txt
lisa_globalfit_framework-0.7.1.dist-info/RECORD
